{
  "release": 243,
  "status": "LOCAL_METADATA_RECONCILED_REMOTE_PR_PENDING",
  "baseCommit": "c69b1ee95bbf87b95a41c51c2428249c0d74533d",
  "requiredCommitTitle": "Release 243: establish verified production baseline and complete repository recovery",
  "declaredChangedCount": 358,
  "declaredAddedCount": 27,
  "declaredModifiedCount": 17,
  "declaredDeletedCount": 314,
  "serviceWorkerRelease": "243",
  "publicationMode": "github-atomic-tree-pull-request",
  "browserUploadAllowed": false,
  "javascriptTests": "18/18",
  "pythonTests": "61/61",
  "legacyDeletedCount": 295,
  "misuploadedPackageDeletedCount": 19,
  "branch": "release-243-production-baseline-recovery",
  "remotePullRequestChecks": "PENDING_RERUN"
}
