{
  "batch": 45,
  "volume": 11,
  "items": [
    {
      "number": 405,
      "slug": "song-0405",
      "title_ta": "திருப்புகழ் பாடல் 405",
      "original_tamil": "",
      "metre": "",
      "raga": "",
      "tala": "",
      "temple": "",
      "status": "source-verification-required"
    },
    {
      "number": 406,
      "slug": "song-0406",
      "title_ta": "திருப்புகழ் பாடல் 406",
      "original_tamil": "",
      "metre": "",
      "raga": "",
      "tala": "",
      "temple": "",
      "status": "source-verification-required"
    }
  ]
}